{
  "BULBASAUR": [1, "grass", "poison", 0.7, 6.9, 1, 318],
  "IVYSAUR": [2, "grass", "poison", 1.0, 13.0, 1, 405],
  "VENUSAUR": [3, "grass", "poison", 2.0, 100.0, 1, 625],
  "CHARMANDER": [4, "fire", "None", 0.6, 8.5, 1, 309],
  "CHARMELEON": [5, "fire", "None", 1.1, 19.0, 1, 405],
  "CHARIZARD": [6, "fire", "flying", 1.7, 90.5, 1, 634],
  "SQUIRTLE": [7, "water", "None", 0.5, 9.0, 1, 314],
  "WARTORTLE": [8, "water", "None", 1.0, 22.5, 1, 405],
  "BLASTOISE": [9, "water", "None", 1.6, 85.5, 1, 630],
  "CATERPIE": [10, "bug", "None", 0.3, 2.9, 1, 195],
  "METAPOD": [11, "bug", "None", 0.7, 9.9, 1, 205],
  "BUTTERFREE": [12, "bug", "flying", 1.1, 32.0, 1, 395],
  "WEEDLE": [13, "bug", "poison", 0.3, 3.2, 1, 195],
  "KAKUNA": [14, "bug", "poison", 0.6, 10.0, 1, 205],
  "BEEDRILL": [15, "bug", "poison", 1.0, 29.5, 1, 495],
  "PIDGEY": [16, "normal", "flying", 0.3, 1.8, 1, 251],
  "PIDGEOTTO": [17, "normal", "flying", 1.1, 30.0, 1, 349],
  "PIDGEOT": [18, "normal", "flying", 1.5, 39.5, 1, 579],
  "RATTATA": [19, "normal", "dark", NaN, NaN, 1, 253],
  "RATICATE": [20, "normal", "dark", NaN, NaN, 1, 413],
  "SPEAROW": [21, "normal", "flying", 0.3, 2.0, 1, 262],
  "FEAROW": [22, "normal", "flying", 1.2, 38.0, 1, 442],
  "EKANS": [23, "poison", "None", 2.0, 6.9, 1, 288],
  "ARBOK": [24, "poison", "None", 3.5, 65.0, 1, 448],
  "PIKACHU": [25, "electric", "None", 0.4, 6.0, 1, 320],
  "RAICHU": [26, "electric", "electric", NaN, NaN, 1, 485],
  "SANDSHREW": [27, "ground", "ice", NaN, NaN, 1, 300],
  "SANDSLASH": [28, "ground", "ice", NaN, NaN, 1, 450],
  "NIDORAN\u2640": [29, "poison", "None", 0.4, 7.0, 1, 275],
  "NIDORINA": [30, "poison", "None", 0.8, 20.0, 1, 365],
  "NIDOQUEEN": [31, "poison", "ground", 1.3, 60.0, 1, 505],
  "NIDORAN\u2642": [32, "poison", "None", 0.5, 9.0, 1, 273],
  "NIDORINO": [33, "poison", "None", 0.9, 19.5, 1, 365],
  "NIDOKING": [34, "poison", "ground", 1.4, 62.0, 1, 505],
  "CLEFAIRY": [35, "fairy", "None", 0.6, 7.5, 1, 323],
  "CLEFABLE": [36, "fairy", "None", 1.3, 40.0, 1, 483],
  "VULPIX": [37, "fire", "ice", NaN, NaN, 1, 299],
  "NINETALES": [38, "fire", "ice", NaN, NaN, 1, 505],
  "JIGGLYPUFF": [39, "normal", "fairy", 0.5, 5.5, 1, 270],
  "WIGGLYTUFF": [40, "normal", "fairy", 1.0, 12.0, 1, 435],
  "ZUBAT": [41, "poison", "flying", 0.8, 7.5, 1, 245],
  "GOLBAT": [42, "poison", "flying", 1.6, 55.0, 1, 455],
  "ODDISH": [43, "grass", "poison", 0.5, 5.4, 1, 320],
  "GLOOM": [44, "grass", "poison", 0.8, 8.6, 1, 395],
  "VILEPLUME": [45, "grass", "poison", 1.2, 18.6, 1, 490],
  "PARAS": [46, "bug", "grass", 0.3, 5.4, 1, 285],
  "PARASECT": [47, "bug", "grass", 1.0, 29.5, 1, 405],
  "VENONAT": [48, "bug", "poison", 1.0, 30.0, 1, 305],
  "VENOMOTH": [49, "bug", "poison", 1.5, 12.5, 1, 450],
  "DIGLETT": [50, "ground", "ground", NaN, NaN, 1, 265],
  "DUGTRIO": [51, "ground", "ground", NaN, NaN, 1, 425],
  "MEOWTH": [52, "normal", "dark", NaN, NaN, 1, 290],
  "PERSIAN": [53, "normal", "dark", NaN, NaN, 1, 440],
  "PSYDUCK": [54, "water", "None", 0.8, 19.6, 1, 320],
  "GOLDUCK": [55, "water", "None", 1.7, 76.6, 1, 500],
  "MANKEY": [56, "fighting", "None", 0.5, 28.0, 1, 305],
  "PRIMEAPE": [57, "fighting", "None", 1.0, 32.0, 1, 455],
  "GROWLITHE": [58, "fire", "None", 0.7, 19.0, 1, 350],
  "ARCANINE": [59, "fire", "None", 1.9, 155.0, 1, 555],
  "POLIWAG": [60, "water", "None", 0.6, 12.4, 1, 300],
  "POLIWHIRL": [61, "water", "None", 1.0, 20.0, 1, 385],
  "POLIWRATH": [62, "water", "fighting", 1.3, 54.0, 1, 510],
  "ABRA": [63, "psychic", "None", 0.9, 19.5, 1, 310],
  "KADABRA": [64, "psychic", "None", 1.3, 56.5, 1, 400],
  "ALAKAZAM": [65, "psychic", "None", 1.5, 48.0, 1, 600],
  "MACHOP": [66, "fighting", "None", 0.8, 19.5, 1, 305],
  "MACHOKE": [67, "fighting", "None", 1.5, 70.5, 1, 405],
  "MACHAMP": [68, "fighting", "None", 1.6, 130.0, 1, 505],
  "BELLSPROUT": [69, "grass", "poison", 0.7, 4.0, 1, 300],
  "WEEPINBELL": [70, "grass", "poison", 1.0, 6.4, 1, 390],
  "VICTREEBEL": [71, "grass", "poison", 1.7, 15.5, 1, 490],
  "TENTACOOL": [72, "water", "poison", 0.9, 45.5, 1, 335],
  "TENTACRUEL": [73, "water", "poison", 1.6, 55.0, 1, 515],
  "GEODUDE": [74, "rock", "ground", NaN, NaN, 1, 300],
  "GRAVELER": [75, "rock", "ground", NaN, NaN, 1, 390],
  "GOLEM": [76, "rock", "ground", NaN, NaN, 1, 495],
  "PONYTA": [77, "fire", "None", 1.0, 30.0, 1, 410],
  "RAPIDASH": [78, "fire", "None", 1.7, 95.0, 1, 500],
  "SLOWPOKE": [79, "water", "psychic", 1.2, 36.0, 1, 315],
  "SLOWBRO": [80, "water", "psychic", 1.6, 78.5, 1, 590],
  "MAGNEMITE": [81, "electric", "steel", 0.3, 6.0, 1, 325],
  "MAGNETON": [82, "electric", "steel", 1.0, 60.0, 1, 465],
  "FARFETCH'D": [83, "normal", "flying", 0.8, 15.0, 1, 377],
  "DODUO": [84, "normal", "flying", 1.4, 39.2, 1, 310],
  "DODRIO": [85, "normal", "flying", 1.8, 85.2, 1, 470],
  "SEEL": [86, "water", "None", 1.1, 90.0, 1, 325],
  "DEWGONG": [87, "water", "ice", 1.7, 120.0, 1, 475],
  "GRIMER": [88, "poison", "poison", NaN, NaN, 1, 325],
  "MUK": [89, "poison", "poison", NaN, NaN, 1, 500],
  "SHELLDER": [90, "water", "None", 0.3, 4.0, 1, 305],
  "CLOYSTER": [91, "water", "ice", 1.5, 132.5, 1, 525],
  "GASTLY": [92, "ghost", "poison", 1.3, 0.1, 1, 310],
  "HAUNTER": [93, "ghost", "poison", 1.6, 0.1, 1, 405],
  "GENGAR": [94, "ghost", "poison", 1.5, 40.5, 1, 600],
  "ONIX": [95, "rock", "ground", 8.8, 210.0, 1, 385],
  "DROWZEE": [96, "psychic", "None", 1.0, 32.4, 1, 328],
  "HYPNO": [97, "psychic", "None", 1.6, 75.6, 1, 483],
  "KRABBY": [98, "water", "None", 0.4, 6.5, 1, 325],
  "KINGLER": [99, "water", "None", 1.3, 60.0, 1, 475],
  "VOLTORB": [100, "electric", "None", 0.5, 10.4, 1, 330],
  "ELECTRODE": [101, "electric", "None", 1.2, 66.6, 1, 490],
  "EXEGGCUTE": [102, "grass", "psychic", 0.4, 2.5, 1, 325],
  "EXEGGUTOR": [103, "grass", "psychic", NaN, NaN, 1, 530],
  "CUBONE": [104, "ground", "None", 0.4, 6.5, 1, 320],
  "MAROWAK": [105, "ground", "fire", NaN, NaN, 1, 425],
  "HITMONLEE": [106, "fighting", "None", 1.5, 49.8, 1, 455],
  "HITMONCHAN": [107, "fighting", "None", 1.4, 50.2, 1, 455],
  "LICKITUNG": [108, "normal", "None", 1.2, 65.5, 1, 385],
  "KOFFING": [109, "poison", "None", 0.6, 1.0, 1, 340],
  "WEEZING": [110, "poison", "None", 1.2, 9.5, 1, 490],
  "RHYHORN": [111, "ground", "rock", 1.0, 115.0, 1, 345],
  "RHYDON": [112, "ground", "rock", 1.9, 120.0, 1, 485],
  "CHANSEY": [113, "normal", "None", 1.1, 34.6, 1, 450],
  "TANGELA": [114, "grass", "None", 1.0, 35.0, 1, 435],
  "KANGASKHAN": [115, "normal", "None", 2.2, 80.0, 1, 590],
  "HORSEA": [116, "water", "None", 0.4, 8.0, 1, 295],
  "SEADRA": [117, "water", "None", 1.2, 25.0, 1, 440],
  "GOLDEEN": [118, "water", "None", 0.6, 15.0, 1, 320],
  "SEAKING": [119, "water", "None", 1.3, 39.0, 1, 450],
  "STARYU": [120, "water", "None", 0.8, 34.5, 1, 340],
  "STARMIE": [121, "water", "psychic", 1.1, 80.0, 1, 520],
  "MR. MIME": [122, "psychic", "fairy", 1.3, 54.5, 1, 460],
  "SCYTHER": [123, "bug", "flying", 1.5, 56.0, 1, 500],
  "JYNX": [124, "ice", "psychic", 1.4, 40.6, 1, 455],
  "ELECTABUZZ": [125, "electric", "None", 1.1, 30.0, 1, 490],
  "MAGMAR": [126, "fire", "None", 1.3, 44.5, 1, 495],
  "PINSIR": [127, "bug", "None", 1.5, 55.0, 1, 600],
  "TAUROS": [128, "normal", "None", 1.4, 88.4, 1, 490],
  "MAGIKARP": [129, "water", "None", 0.9, 10.0, 1, 200],
  "GYARADOS": [130, "water", "flying", 6.5, 235.0, 1, 640],
  "LAPRAS": [131, "water", "ice", 2.5, 220.0, 1, 535],
  "DITTO": [132, "normal", "None", 0.3, 4.0, 1, 288],
  "EEVEE": [133, "normal", "None", 0.3, 6.5, 1, 325],
  "VAPOREON": [134, "water", "None", 1.0, 29.0, 1, 525],
  "JOLTEON": [135, "electric", "None", 0.8, 24.5, 1, 525],
  "FLAREON": [136, "fire", "None", 0.9, 25.0, 1, 525],
  "PORYGON": [137, "normal", "None", 0.8, 36.5, 1, 395],
  "OMANYTE": [138, "rock", "water", 0.4, 7.5, 1, 355],
  "OMASTAR": [139, "rock", "water", 1.0, 35.0, 1, 495],
  "KABUTO": [140, "rock", "water", 0.5, 11.5, 1, 355],
  "KABUTOPS": [141, "rock", "water", 1.3, 40.5, 1, 495],
  "AERODACTYL": [142, "rock", "flying", 1.8, 59.0, 1, 615],
  "SNORLAX": [143, "normal", "None", 2.1, 460.0, 1, 540],
  "ARTICUNO": [144, "ice", "flying", 1.7, 55.4, 1, 580],
  "ZAPDOS": [145, "electric", "flying", 1.6, 52.6, 1, 580],
  "MOLTRES": [146, "fire", "flying", 2.0, 60.0, 1, 580],
  "DRATINI": [147, "dragon", "None", 1.8, 3.3, 1, 300],
  "DRAGONAIR": [148, "dragon", "None", 4.0, 16.5, 1, 420],
  "DRAGONITE": [149, "dragon", "flying", 2.2, 210.0, 1, 600],
  "MEWTWO": [150, "psychic", "None", 2.0, 122.0, 1, 780],
  "MEW": [151, "psychic", "None", 0.4, 4.0, 1, 600],
  "CHIKORITA": [152, "grass", "None", 0.9, 6.4, 2, 318],
  "BAYLEEF": [153, "grass", "None", 1.2, 15.8, 2, 405],
  "MEGANIUM": [154, "grass", "None", 1.8, 100.5, 2, 525],
  "CYNDAQUIL": [155, "fire", "None", 0.5, 7.9, 2, 309],
  "QUILAVA": [156, "fire", "None", 0.9, 19.0, 2, 405],
  "TYPHLOSION": [157, "fire", "None", 1.7, 79.5, 2, 534],
  "TOTODILE": [158, "water", "None", 0.6, 9.5, 2, 314],
  "CROCONAW": [159, "water", "None", 1.1, 25.0, 2, 405],
  "FERALIGATR": [160, "water", "None", 2.3, 88.8, 2, 530],
  "SENTRET": [161, "normal", "None", 0.8, 6.0, 2, 215],
  "FURRET": [162, "normal", "None", 1.8, 32.5, 2, 415],
  "HOOTHOOT": [163, "normal", "flying", 0.7, 21.2, 2, 262],
  "NOCTOWL": [164, "normal", "flying", 1.6, 40.8, 2, 452],
  "LEDYBA": [165, "bug", "flying", 1.0, 10.8, 2, 265],
  "LEDIAN": [166, "bug", "flying", 1.4, 35.6, 2, 390],
  "SPINARAK": [167, "bug", "poison", 0.5, 8.5, 2, 250],
  "ARIADOS": [168, "bug", "poison", 1.1, 33.5, 2, 400],
  "CROBAT": [169, "poison", "flying", 1.8, 75.0, 2, 535],
  "CHINCHOU": [170, "water", "electric", 0.5, 12.0, 2, 330],
  "LANTURN": [171, "water", "electric", 1.2, 22.5, 2, 460],
  "PICHU": [172, "electric", "None", 0.3, 2.0, 2, 205],
  "CLEFFA": [173, "fairy", "None", 0.3, 3.0, 2, 218],
  "IGGLYBUFF": [174, "normal", "fairy", 0.3, 1.0, 2, 210],
  "TOGEPI": [175, "fairy", "None", 0.3, 1.5, 2, 245],
  "TOGETIC": [176, "fairy", "flying", 0.6, 3.2, 2, 405],
  "NATU": [177, "psychic", "flying", 0.2, 2.0, 2, 320],
  "XATU": [178, "psychic", "flying", 1.5, 15.0, 2, 470],
  "MAREEP": [179, "electric", "None", 0.6, 7.8, 2, 280],
  "FLAAFFY": [180, "electric", "None", 0.8, 13.3, 2, 365],
  "AMPHAROS": [181, "electric", "None", 1.4, 61.5, 2, 610],
  "BELLOSSOM": [182, "grass", "None", 0.4, 5.8, 2, 490],
  "MARILL": [183, "water", "fairy", 0.4, 8.5, 2, 250],
  "AZUMARILL": [184, "water", "fairy", 0.8, 28.5, 2, 420],
  "SUDOWOODO": [185, "rock", "None", 1.2, 38.0, 2, 410],
  "POLITOED": [186, "water", "None", 1.1, 33.9, 2, 500],
  "HOPPIP": [187, "grass", "flying", 0.4, 0.5, 2, 250],
  "SKIPLOOM": [188, "grass", "flying", 0.6, 1.0, 2, 340],
  "JUMPLUFF": [189, "grass", "flying", 0.8, 3.0, 2, 460],
  "AIPOM": [190, "normal", "None", 0.8, 11.5, 2, 360],
  "SUNKERN": [191, "grass", "None", 0.3, 1.8, 2, 180],
  "SUNFLORA": [192, "grass", "None", 0.8, 8.5, 2, 425],
  "YANMA": [193, "bug", "flying", 1.2, 38.0, 2, 390],
  "WOOPER": [194, "water", "ground", 0.4, 8.5, 2, 210],
  "QUAGSIRE": [195, "water", "ground", 1.4, 75.0, 2, 430],
  "ESPEON": [196, "psychic", "None", 0.9, 26.5, 2, 525],
  "UMBREON": [197, "dark", "None", 1.0, 27.0, 2, 525],
  "MURKROW": [198, "dark", "flying", 0.5, 2.1, 2, 405],
  "SLOWKING": [199, "water", "psychic", 2.0, 79.5, 2, 490],
  "MISDREAVUS": [200, "ghost", "None", 0.7, 1.0, 2, 435],
  "UNOWN": [201, "psychic", "None", 0.5, 5.0, 2, 336],
  "WOBBUFFET": [202, "psychic", "None", 1.3, 28.5, 2, 405],
  "GIRAFARIG": [203, "normal", "psychic", 1.5, 41.5, 2, 455],
  "PINECO": [204, "bug", "None", 0.6, 7.2, 2, 290],
  "FORRETRESS": [205, "bug", "steel", 1.2, 125.8, 2, 465],
  "DUNSPARCE": [206, "normal", "None", 1.5, 14.0, 2, 415],
  "GLIGAR": [207, "ground", "flying", 1.1, 64.8, 2, 430],
  "STEELIX": [208, "steel", "ground", 9.2, 400.0, 2, 610],
  "SNUBBULL": [209, "fairy", "None", 0.6, 7.8, 2, 300],
  "GRANBULL": [210, "fairy", "None", 1.4, 48.7, 2, 450],
  "QWILFISH": [211, "water", "poison", 0.5, 3.9, 2, 440],
  "SCIZOR": [212, "bug", "steel", 1.8, 118.0, 2, 600],
  "SHUCKLE": [213, "bug", "rock", 0.6, 20.5, 2, 505],
  "HERACROSS": [214, "bug", "fighting", 1.5, 54.0, 2, 600],
  "SNEASEL": [215, "dark", "ice", 0.9, 28.0, 2, 430],
  "TEDDIURSA": [216, "normal", "None", 0.6, 8.8, 2, 330],
  "URSARING": [217, "normal", "None", 1.8, 125.8, 2, 500],
  "SLUGMA": [218, "fire", "None", 0.7, 35.0, 2, 250],
  "MAGCARGO": [219, "fire", "rock", 0.8, 55.0, 2, 430],
  "SWINUB": [220, "ice", "ground", 0.4, 6.5, 2, 250],
  "PILOSWINE": [221, "ice", "ground", 1.1, 55.8, 2, 450],
  "CORSOLA": [222, "water", "rock", 0.6, 5.0, 2, 410],
  "REMORAID": [223, "water", "None", 0.6, 12.0, 2, 300],
  "OCTILLERY": [224, "water", "None", 0.9, 28.5, 2, 480],
  "DELIBIRD": [225, "ice", "flying", 0.9, 16.0, 2, 330],
  "MANTINE": [226, "water", "flying", 2.1, 220.0, 2, 485],
  "SKARMORY": [227, "steel", "flying", 1.7, 50.5, 2, 465],
  "HOUNDOUR": [228, "dark", "fire", 0.6, 10.8, 2, 330],
  "HOUNDOOM": [229, "dark", "fire", 1.4, 35.0, 2, 600],
  "KINGDRA": [230, "water", "dragon", 1.8, 152.0, 2, 540],
  "PHANPY": [231, "ground", "None", 0.5, 33.5, 2, 330],
  "DONPHAN": [232, "ground", "None", 1.1, 120.0, 2, 500],
  "PORYGON2": [233, "normal", "None", 0.6, 32.5, 2, 515],
  "STANTLER": [234, "normal", "None", 1.4, 71.2, 2, 465],
  "SMEARGLE": [235, "normal", "None", 1.2, 58.0, 2, 250],
  "TYROGUE": [236, "fighting", "None", 0.7, 21.0, 2, 210],
  "HITMONTOP": [237, "fighting", "None", 1.4, 48.0, 2, 455],
  "SMOOCHUM": [238, "ice", "psychic", 0.4, 6.0, 2, 305],
  "ELEKID": [239, "electric", "None", 0.6, 23.5, 2, 360],
  "MAGBY": [240, "fire", "None", 0.7, 21.4, 2, 365],
  "MILTANK": [241, "normal", "None", 1.2, 75.5, 2, 490],
  "BLISSEY": [242, "normal", "None", 1.5, 46.8, 2, 540],
  "RAIKOU": [243, "electric", "None", 1.9, 178.0, 2, 580],
  "ENTEI": [244, "fire", "None", 2.1, 198.0, 2, 580],
  "SUICUNE": [245, "water", "None", 2.0, 187.0, 2, 580],
  "LARVITAR": [246, "rock", "ground", 0.6, 72.0, 2, 300],
  "PUPITAR": [247, "rock", "ground", 1.2, 152.0, 2, 410],
  "TYRANITAR": [248, "rock", "dark", 2.0, 202.0, 2, 700],
  "LUGIA": [249, "psychic", "flying", 5.2, 216.0, 2, 680],
  "HO-OH": [250, "fire", "flying", 3.8, 199.0, 2, 680],
  "CELEBI": [251, "psychic", "grass", 0.6, 5.0, 2, 600],
  "TREECKO": [252, "grass", "None", 0.5, 5.0, 3, 310],
  "GROVYLE": [253, "grass", "None", 0.9, 21.6, 3, 405],
  "SCEPTILE": [254, "grass", "None", 1.7, 52.2, 3, 630],
  "TORCHIC": [255, "fire", "None", 0.4, 2.5, 3, 310],
  "COMBUSKEN": [256, "fire", "fighting", 0.9, 19.5, 3, 405],
  "BLAZIKEN": [257, "fire", "fighting", 1.9, 52.0, 3, 630],
  "MUDKIP": [258, "water", "None", 0.4, 7.6, 3, 310],
  "MARSHTOMP": [259, "water", "ground", 0.7, 28.0, 3, 405],
  "SWAMPERT": [260, "water", "ground", 1.5, 81.9, 3, 635],
  "POOCHYENA": [261, "dark", "None", 0.5, 13.6, 3, 220],
  "MIGHTYENA": [262, "dark", "None", 1.0, 37.0, 3, 420],
  "ZIGZAGOON": [263, "normal", "None", 0.4, 17.5, 3, 240],
  "LINOONE": [264, "normal", "None", 0.5, 32.5, 3, 420],
  "WURMPLE": [265, "bug", "None", 0.3, 3.6, 3, 195],
  "SILCOON": [266, "bug", "None", 0.6, 10.0, 3, 205],
  "BEAUTIFLY": [267, "bug", "flying", 1.0, 28.4, 3, 395],
  "CASCOON": [268, "bug", "None", 0.7, 11.5, 3, 205],
  "DUSTOX": [269, "bug", "poison", 1.2, 31.6, 3, 385],
  "LOTAD": [270, "water", "grass", 0.5, 2.6, 3, 220],
  "LOMBRE": [271, "water", "grass", 1.2, 32.5, 3, 340],
  "LUDICOLO": [272, "water", "grass", 1.5, 55.0, 3, 480],
  "SEEDOT": [273, "grass", "None", 0.5, 4.0, 3, 220],
  "NUZLEAF": [274, "grass", "dark", 1.0, 28.0, 3, 340],
  "SHIFTRY": [275, "grass", "dark", 1.3, 59.6, 3, 480],
  "TAILLOW": [276, "normal", "flying", 0.3, 2.3, 3, 270],
  "SWELLOW": [277, "normal", "flying", 0.7, 19.8, 3, 455],
  "WINGULL": [278, "water", "flying", 0.6, 9.5, 3, 270],
  "PELIPPER": [279, "water", "flying", 1.2, 28.0, 3, 440],
  "RALTS": [280, "psychic", "fairy", 0.4, 6.6, 3, 198],
  "KIRLIA": [281, "psychic", "fairy", 0.8, 20.2, 3, 278],
  "GARDEVOIR": [282, "psychic", "fairy", 1.6, 48.4, 3, 618],
  "SURSKIT": [283, "bug", "water", 0.5, 1.7, 3, 269],
  "MASQUERAIN": [284, "bug", "flying", 0.8, 3.6, 3, 454],
  "SHROOMISH": [285, "grass", "None", 0.4, 4.5, 3, 295],
  "BRELOOM": [286, "grass", "fighting", 1.2, 39.2, 3, 460],
  "SLAKOTH": [287, "normal", "None", 0.8, 24.0, 3, 280],
  "VIGOROTH": [288, "normal", "None", 1.4, 46.5, 3, 440],
  "SLAKING": [289, "normal", "None", 2.0, 130.5, 3, 670],
  "NINCADA": [290, "bug", "ground", 0.5, 5.5, 3, 266],
  "NINJASK": [291, "bug", "flying", 0.8, 12.0, 3, 456],
  "SHEDINJA": [292, "bug", "ghost", 0.8, 1.2, 3, 236],
  "WHISMUR": [293, "normal", "None", 0.6, 16.3, 3, 240],
  "LOUDRED": [294, "normal", "None", 1.0, 40.5, 3, 360],
  "EXPLOUD": [295, "normal", "None", 1.5, 84.0, 3, 490],
  "MAKUHITA": [296, "fighting", "None", 1.0, 86.4, 3, 237],
  "HARIYAMA": [297, "fighting", "None", 2.3, 253.8, 3, 474],
  "AZURILL": [298, "normal", "fairy", 0.2, 2.0, 3, 190],
  "NOSEPASS": [299, "rock", "None", 1.0, 97.0, 3, 375],
  "SKITTY": [300, "normal", "None", 0.6, 11.0, 3, 260],
  "DELCATTY": [301, "normal", "None", 1.1, 32.6, 3, 400],
  "SABLEYE": [302, "dark", "ghost", 0.5, 11.0, 3, 480],
  "MAWILE": [303, "steel", "fairy", 0.6, 11.5, 3, 480],
  "ARON": [304, "steel", "rock", 0.4, 60.0, 3, 330],
  "LAIRON": [305, "steel", "rock", 0.9, 120.0, 3, 430],
  "AGGRON": [306, "steel", "rock", 2.1, 360.0, 3, 630],
  "MEDITITE": [307, "fighting", "psychic", 0.6, 11.2, 3, 280],
  "MEDICHAM": [308, "fighting", "psychic", 1.3, 31.5, 3, 510],
  "ELECTRIKE": [309, "electric", "None", 0.6, 15.2, 3, 295],
  "MANECTRIC": [310, "electric", "None", 1.5, 40.2, 3, 575],
  "PLUSLE": [311, "electric", "None", 0.4, 4.2, 3, 405],
  "MINUN": [312, "electric", "None", 0.4, 4.2, 3, 405],
  "VOLBEAT": [313, "bug", "None", 0.7, 17.7, 3, 430],
  "ILLUMISE": [314, "bug", "None", 0.6, 17.7, 3, 430],
  "ROSELIA": [315, "grass", "poison", 0.3, 2.0, 3, 400],
  "GULPIN": [316, "poison", "None", 0.4, 10.3, 3, 302],
  "SWALOT": [317, "poison", "None", 1.7, 80.0, 3, 467],
  "CARVANHA": [318, "water", "dark", 0.8, 20.8, 3, 305],
  "SHARPEDO": [319, "water", "dark", 1.8, 88.8, 3, 560],
  "WAILMER": [320, "water", "None", 2.0, 130.0, 3, 400],
  "WAILORD": [321, "water", "None", 14.5, 398.0, 3, 500],
  "NUMEL": [322, "fire", "ground", 0.7, 24.0, 3, 305],
  "CAMERUPT": [323, "fire", "ground", 1.9, 220.0, 3, 560],
  "TORKOAL": [324, "fire", "None", 0.5, 80.4, 3, 470],
  "SPOINK": [325, "psychic", "None", 0.7, 30.6, 3, 330],
  "GRUMPIG": [326, "psychic", "None", 0.9, 71.5, 3, 470],
  "SPINDA": [327, "normal", "None", 1.1, 5.0, 3, 360],
  "TRAPINCH": [328, "ground", "None", 0.7, 15.0, 3, 290],
  "VIBRAVA": [329, "ground", "dragon", 1.1, 15.3, 3, 340],
  "FLYGON": [330, "ground", "dragon", 2.0, 82.0, 3, 520],
  "CACNEA": [331, "grass", "None", 0.4, 51.3, 3, 335],
  "CACTURNE": [332, "grass", "dark", 1.3, 77.4, 3, 475],
  "SWABLU": [333, "normal", "flying", 0.4, 1.2, 3, 310],
  "ALTARIA": [334, "dragon", "flying", 1.1, 20.6, 3, 590],
  "ZANGOOSE": [335, "normal", "None", 1.3, 40.3, 3, 458],
  "SEVIPER": [336, "poison", "None", 2.7, 52.5, 3, 458],
  "LUNATONE": [337, "rock", "psychic", 1.0, 168.0, 3, 460],
  "SOLROCK": [338, "rock", "psychic", 1.2, 154.0, 3, 460],
  "BARBOACH": [339, "water", "ground", 0.4, 1.9, 3, 288],
  "WHISCASH": [340, "water", "ground", 0.9, 23.6, 3, 468],
  "CORPHISH": [341, "water", "None", 0.6, 11.5, 3, 308],
  "CRAWDAUNT": [342, "water", "dark", 1.1, 32.8, 3, 468],
  "BALTOY": [343, "ground", "psychic", 0.5, 21.5, 3, 300],
  "CLAYDOL": [344, "ground", "psychic", 1.5, 108.0, 3, 500],
  "LILEEP": [345, "rock", "grass", 1.0, 23.8, 3, 355],
  "CRADILY": [346, "rock", "grass", 1.5, 60.4, 3, 495],
  "ANORITH": [347, "rock", "bug", 0.7, 12.5, 3, 355],
  "ARMALDO": [348, "rock", "bug", 1.5, 68.2, 3, 495],
  "FEEBAS": [349, "water", "None", 0.6, 7.4, 3, 200],
  "MILOTIC": [350, "water", "None", 6.2, 162.0, 3, 540],
  "CASTFORM": [351, "normal", "None", 0.3, 0.8, 3, 420],
  "KECLEON": [352, "normal", "None", 1.0, 22.0, 3, 440],
  "SHUPPET": [353, "ghost", "None", 0.6, 2.3, 3, 295],
  "BANETTE": [354, "ghost", "None", 1.1, 12.5, 3, 555],
  "DUSKULL": [355, "ghost", "None", 0.8, 15.0, 3, 295],
  "DUSCLOPS": [356, "ghost", "None", 1.6, 30.6, 3, 455],
  "TROPIUS": [357, "grass", "flying", 2.0, 100.0, 3, 460],
  "CHIMECHO": [358, "psychic", "None", 0.6, 1.0, 3, 455],
  "ABSOL": [359, "dark", "None", 1.2, 47.0, 3, 565],
  "WYNAUT": [360, "psychic", "None", 0.6, 14.0, 3, 260],
  "SNORUNT": [361, "ice", "None", 0.7, 16.8, 3, 300],
  "GLALIE": [362, "ice", "None", 1.5, 256.5, 3, 580],
  "SPHEAL": [363, "ice", "water", 0.8, 39.5, 3, 290],
  "SEALEO": [364, "ice", "water", 1.1, 87.6, 3, 410],
  "WALREIN": [365, "ice", "water", 1.4, 150.6, 3, 530],
  "CLAMPERL": [366, "water", "None", 0.4, 52.5, 3, 345],
  "HUNTAIL": [367, "water", "None", 1.7, 27.0, 3, 485],
  "GOREBYSS": [368, "water", "None", 1.8, 22.6, 3, 485],
  "RELICANTH": [369, "water", "rock", 1.0, 23.4, 3, 485],
  "LUVDISC": [370, "water", "None", 0.6, 8.7, 3, 330],
  "BAGON": [371, "dragon", "None", 0.6, 42.1, 3, 300],
  "SHELGON": [372, "dragon", "None", 1.1, 110.5, 3, 420],
  "SALAMENCE": [373, "dragon", "flying", 1.5, 102.6, 3, 700],
  "BELDUM": [374, "steel", "psychic", 0.6, 95.2, 3, 300],
  "METANG": [375, "steel", "psychic", 1.2, 202.5, 3, 420],
  "METAGROSS": [376, "steel", "psychic", 1.6, 550.0, 3, 700],
  "REGIROCK": [377, "rock", "None", 1.7, 230.0, 3, 580],
  "REGICE": [378, "ice", "None", 1.8, 175.0, 3, 580],
  "REGISTEEL": [379, "steel", "None", 1.9, 205.0, 3, 580],
  "LATIAS": [380, "dragon", "psychic", 1.4, 40.0, 3, 700],
  "LATIOS": [381, "dragon", "psychic", 2.0, 60.0, 3, 700],
  "KYOGRE": [382, "water", "None", 4.5, 352.0, 3, 770],
  "GROUDON": [383, "ground", "None", 3.5, 950.0, 3, 770],
  "RAYQUAZA": [384, "dragon", "flying", 7.0, 206.5, 3, 780],
  "JIRACHI": [385, "steel", "psychic", 0.3, 1.1, 3, 600],
  "DEOXYS": [386, "psychic", "None", 1.7, 60.8, 3, 600],
  "TURTWIG": [387, "grass", "None", 0.4, 10.2, 4, 318],
  "GROTLE": [388, "grass", "None", 1.1, 97.0, 4, 405],
  "TORTERRA": [389, "grass", "ground", 2.2, 310.0, 4, 525],
  "CHIMCHAR": [390, "fire", "None", 0.5, 6.2, 4, 309],
  "MONFERNO": [391, "fire", "fighting", 0.9, 22.0, 4, 405],
  "INFERNAPE": [392, "fire", "fighting", 1.2, 55.0, 4, 534],
  "PIPLUP": [393, "water", "None", 0.4, 5.2, 4, 314],
  "PRINPLUP": [394, "water", "None", 0.8, 23.0, 4, 405],
  "EMPOLEON": [395, "water", "steel", 1.7, 84.5, 4, 530],
  "STARLY": [396, "normal", "flying", 0.3, 2.0, 4, 245],
  "STARAVIA": [397, "normal", "flying", 0.6, 15.5, 4, 340],
  "STARAPTOR": [398, "normal", "flying", 1.2, 24.9, 4, 485],
  "BIDOOF": [399, "normal", "None", 0.5, 20.0, 4, 250],
  "BIBAREL": [400, "normal", "water", 1.0, 31.5, 4, 410],
  "KRICKETOT": [401, "bug", "None", 0.3, 2.2, 4, 194],
  "KRICKETUNE": [402, "bug", "None", 1.0, 25.5, 4, 384],
  "SHINX": [403, "electric", "None", 0.5, 9.5, 4, 263],
  "LUXIO": [404, "electric", "None", 0.9, 30.5, 4, 363],
  "LUXRAY": [405, "electric", "None", 1.4, 42.0, 4, 523],
  "BUDEW": [406, "grass", "poison", 0.2, 1.2, 4, 280],
  "ROSERADE": [407, "grass", "poison", 0.9, 14.5, 4, 515],
  "CRANIDOS": [408, "rock", "None", 0.9, 31.5, 4, 350],
  "RAMPARDOS": [409, "rock", "None", 1.6, 102.5, 4, 495],
  "SHIELDON": [410, "rock", "steel", 0.5, 57.0, 4, 350],
  "BASTIODON": [411, "rock", "steel", 1.3, 149.5, 4, 495],
  "BURMY": [412, "bug", "None", 0.2, 3.4, 4, 224],
  "WORMADAM": [413, "bug", "grass", 0.5, 6.5, 4, 424],
  "MOTHIM": [414, "bug", "flying", 0.9, 23.3, 4, 424],
  "COMBEE": [415, "bug", "flying", 0.3, 5.5, 4, 244],
  "VESPIQUEN": [416, "bug", "flying", 1.2, 38.5, 4, 474],
  "PACHIRISU": [417, "electric", "None", 0.4, 3.9, 4, 405],
  "BUIZEL": [418, "water", "None", 0.7, 29.5, 4, 330],
  "FLOATZEL": [419, "water", "None", 1.1, 33.5, 4, 495],
  "CHERUBI": [420, "grass", "None", 0.4, 3.3, 4, 275],
  "CHERRIM": [421, "grass", "None", 0.5, 9.3, 4, 450],
  "SHELLOS": [422, "water", "None", 0.3, 6.3, 4, 325],
  "GASTRODON": [423, "water", "ground", 0.9, 29.9, 4, 475],
  "AMBIPOM": [424, "normal", "None", 1.2, 20.3, 4, 482],
  "DRIFLOON": [425, "ghost", "flying", 0.4, 1.2, 4, 348],
  "DRIFBLIM": [426, "ghost", "flying", 1.2, 15.0, 4, 498],
  "BUNEARY": [427, "normal", "None", 0.4, 5.5, 4, 350],
  "LOPUNNY": [428, "normal", "None", 1.2, 33.3, 4, 580],
  "MISMAGIUS": [429, "ghost", "None", 0.9, 4.4, 4, 495],
  "HONCHKROW": [430, "dark", "flying", 0.9, 27.3, 4, 505],
  "GLAMEOW": [431, "normal", "None", 0.5, 3.9, 4, 310],
  "PURUGLY": [432, "normal", "None", 1.0, 43.8, 4, 452],
  "CHINGLING": [433, "psychic", "None", 0.2, 0.6, 4, 285],
  "STUNKY": [434, "poison", "dark", 0.4, 19.2, 4, 329],
  "SKUNTANK": [435, "poison", "dark", 1.0, 38.0, 4, 479],
  "BRONZOR": [436, "steel", "psychic", 0.5, 60.5, 4, 300],
  "BRONZONG": [437, "steel", "psychic", 1.3, 187.0, 4, 500],
  "BONSLY": [438, "rock", "None", 0.5, 15.0, 4, 290],
  "MIME JR.": [439, "psychic", "fairy", 0.6, 13.0, 4, 310],
  "HAPPINY": [440, "normal", "None", 0.6, 24.4, 4, 220],
  "CHATOT": [441, "normal", "flying", 0.5, 1.9, 4, 411],
  "SPIRITOMB": [442, "ghost", "dark", 1.0, 108.0, 4, 485],
  "GIBLE": [443, "dragon", "ground", 0.7, 20.5, 4, 300],
  "GABITE": [444, "dragon", "ground", 1.4, 56.0, 4, 410],
  "GARCHOMP": [445, "dragon", "ground", 1.9, 95.0, 4, 700],
  "MUNCHLAX": [446, "normal", "None", 0.6, 105.0, 4, 390],
  "RIOLU": [447, "fighting", "None", 0.7, 20.2, 4, 285],
  "LUCARIO": [448, "fighting", "steel", 1.2, 54.0, 4, 625],
  "HIPPOPOTAS": [449, "ground", "None", 0.8, 49.5, 4, 330],
  "HIPPOWDON": [450, "ground", "None", 2.0, 300.0, 4, 525],
  "SKORUPI": [451, "poison", "bug", 0.8, 12.0, 4, 330],
  "DRAPION": [452, "poison", "dark", 1.3, 61.5, 4, 500],
  "CROAGUNK": [453, "poison", "fighting", 0.7, 23.0, 4, 300],
  "TOXICROAK": [454, "poison", "fighting", 1.3, 44.4, 4, 490],
  "CARNIVINE": [455, "grass", "None", 1.4, 27.0, 4, 454],
  "FINNEON": [456, "water", "None", 0.4, 7.0, 4, 330],
  "LUMINEON": [457, "water", "None", 1.2, 24.0, 4, 460],
  "MANTYKE": [458, "water", "flying", 1.0, 65.0, 4, 345],
  "SNOVER": [459, "grass", "ice", 1.0, 50.5, 4, 334],
  "ABOMASNOW": [460, "grass", "ice", 2.2, 135.5, 4, 594],
  "WEAVILE": [461, "dark", "ice", 1.1, 34.0, 4, 510],
  "MAGNEZONE": [462, "electric", "steel", 1.2, 180.0, 4, 535],
  "LICKILICKY": [463, "normal", "None", 1.7, 140.0, 4, 515],
  "RHYPERIOR": [464, "ground", "rock", 2.4, 282.8, 4, 535],
  "TANGROWTH": [465, "grass", "None", 2.0, 128.6, 4, 535],
  "ELECTIVIRE": [466, "electric", "None", 1.8, 138.6, 4, 540],
  "MAGMORTAR": [467, "fire", "None", 1.6, 68.0, 4, 540],
  "TOGEKISS": [468, "fairy", "flying", 1.5, 38.0, 4, 545],
  "YANMEGA": [469, "bug", "flying", 1.9, 51.5, 4, 515],
  "LEAFEON": [470, "grass", "None", 1.0, 25.5, 4, 525],
  "GLACEON": [471, "ice", "None", 0.8, 25.9, 4, 525],
  "GLISCOR": [472, "ground", "flying", 2.0, 42.5, 4, 510],
  "MAMOSWINE": [473, "ice", "ground", 2.5, 291.0, 4, 530],
  "PORYGON-Z": [474, "normal", "None", 0.9, 34.0, 4, 535],
  "GALLADE": [475, "psychic", "fighting", 1.6, 52.0, 4, 618],
  "PROBOPASS": [476, "rock", "steel", 1.4, 340.0, 4, 525],
  "DUSKNOIR": [477, "ghost", "None", 2.2, 106.6, 4, 525],
  "FROSLASS": [478, "ice", "ghost", 1.3, 26.6, 4, 480],
  "ROTOM": [479, "electric", "ghost", 0.3, 0.3, 4, 520],
  "UXIE": [480, "psychic", "None", 0.3, 0.3, 4, 580],
  "MESPRIT": [481, "psychic", "None", 0.3, 0.3, 4, 580],
  "AZELF": [482, "psychic", "None", 0.3, 0.3, 4, 580],
  "DIALGA": [483, "steel", "dragon", 5.4, 683.0, 4, 680],
  "PALKIA": [484, "water", "dragon", 4.2, 336.0, 4, 680],
  "HEATRAN": [485, "fire", "steel", 1.7, 430.0, 4, 600],
  "REGIGIGAS": [486, "normal", "None", 3.7, 420.0, 4, 670],
  "GIRATINA": [487, "ghost", "dragon", 4.5, 750.0, 4, 680],
  "CRESSELIA": [488, "psychic", "None", 1.5, 85.6, 4, 600],
  "PHIONE": [489, "water", "None", 0.4, 3.1, 4, 480],
  "MANAPHY": [490, "water", "None", 0.3, 1.4, 4, 600],
  "DARKRAI": [491, "dark", "None", 1.5, 50.5, 4, 600],
  "SHAYMIN": [492, "grass", "grass", 0.2, 2.1, 4, 600],
  "ARCEUS": [493, "normal", "None", 3.2, 320.0, 4, 720],
  "VICTINI": [494, "psychic", "fire", 0.4, 4.0, 5, 600],
  "SNIVY": [495, "grass", "None", 0.6, 8.1, 5, 308],
  "SERVINE": [496, "grass", "None", 0.8, 16.0, 5, 413],
  "SERPERIOR": [497, "grass", "None", 3.3, 63.0, 5, 528],
  "TEPIG": [498, "fire", "None", 0.5, 9.9, 5, 308],
  "PIGNITE": [499, "fire", "fighting", 1.0, 55.5, 5, 418],
  "EMBOAR": [500, "fire", "fighting", 1.6, 150.0, 5, 528],
  "OSHAWOTT": [501, "water", "None", 0.5, 5.9, 5, 308],
  "DEWOTT": [502, "water", "None", 0.8, 24.5, 5, 413],
  "SAMUROTT": [503, "water", "None", 1.5, 94.6, 5, 528],
  "PATRAT": [504, "normal", "None", 0.5, 11.6, 5, 255],
  "WATCHOG": [505, "normal", "None", 1.1, 27.0, 5, 420],
  "LILLIPUP": [506, "normal", "None", 0.4, 4.1, 5, 275],
  "HERDIER": [507, "normal", "None", 0.9, 14.7, 5, 370],
  "STOUTLAND": [508, "normal", "None", 1.2, 61.0, 5, 500],
  "PURRLOIN": [509, "dark", "None", 0.4, 10.1, 5, 281],
  "LIEPARD": [510, "dark", "None", 1.1, 37.5, 5, 446],
  "PANSAGE": [511, "grass", "None", 0.6, 10.5, 5, 316],
  "SIMISAGE": [512, "grass", "None", 1.1, 30.5, 5, 498],
  "PANSEAR": [513, "fire", "None", 0.6, 11.0, 5, 316],
  "SIMISEAR": [514, "fire", "None", 1.0, 28.0, 5, 498],
  "PANPOUR": [515, "water", "None", 0.6, 13.5, 5, 316],
  "SIMIPOUR": [516, "water", "None", 1.0, 29.0, 5, 498],
  "MUNNA": [517, "psychic", "None", 0.6, 23.3, 5, 292],
  "MUSHARNA": [518, "psychic", "None", 1.1, 60.5, 5, 487],
  "PIDOVE": [519, "normal", "flying", 0.3, 2.1, 5, 264],
  "TRANQUILL": [520, "normal", "flying", 0.6, 15.0, 5, 358],
  "UNFEZANT": [521, "normal", "flying", 1.2, 29.0, 5, 488],
  "BLITZLE": [522, "electric", "None", 0.8, 29.8, 5, 295],
  "ZEBSTRIKA": [523, "electric", "None", 1.6, 79.5, 5, 497],
  "ROGGENROLA": [524, "rock", "None", 0.4, 18.0, 5, 280],
  "BOLDORE": [525, "rock", "None", 0.9, 102.0, 5, 390],
  "GIGALITH": [526, "rock", "None", 1.7, 260.0, 5, 515],
  "WOOBAT": [527, "psychic", "flying", 0.4, 2.1, 5, 323],
  "SWOOBAT": [528, "psychic", "flying", 0.9, 10.5, 5, 425],
  "DRILBUR": [529, "ground", "None", 0.3, 8.5, 5, 328],
  "EXCADRILL": [530, "ground", "steel", 0.7, 40.4, 5, 508],
  "AUDINO": [531, "normal", "None", 1.1, 31.0, 5, 545],
  "TIMBURR": [532, "fighting", "None", 0.6, 12.5, 5, 305],
  "GURDURR": [533, "fighting", "None", 1.2, 40.0, 5, 405],
  "CONKELDURR": [534, "fighting", "None", 1.4, 87.0, 5, 505],
  "TYMPOLE": [535, "water", "None", 0.5, 4.5, 5, 294],
  "PALPITOAD": [536, "water", "ground", 0.8, 17.0, 5, 384],
  "SEISMITOAD": [537, "water", "ground", 1.5, 62.0, 5, 509],
  "THROH": [538, "fighting", "None", 1.3, 55.5, 5, 465],
  "SAWK": [539, "fighting", "None", 1.4, 51.0, 5, 465],
  "SEWADDLE": [540, "bug", "grass", 0.3, 2.5, 5, 310],
  "SWADLOON": [541, "bug", "grass", 0.5, 7.3, 5, 380],
  "LEAVANNY": [542, "bug", "grass", 1.2, 20.5, 5, 500],
  "VENIPEDE": [543, "bug", "poison", 0.4, 5.3, 5, 260],
  "WHIRLIPEDE": [544, "bug", "poison", 1.2, 58.5, 5, 360],
  "SCOLIPEDE": [545, "bug", "poison", 2.5, 200.5, 5, 485],
  "COTTONEE": [546, "grass", "fairy", 0.3, 0.6, 5, 280],
  "WHIMSICOTT": [547, "grass", "fairy", 0.7, 6.6, 5, 480],
  "PETILIL": [548, "grass", "None", 0.5, 6.6, 5, 280],
  "LILLIGANT": [549, "grass", "None", 1.1, 16.3, 5, 480],
  "BASCULIN": [550, "water", "None", 1.0, 18.0, 5, 460],
  "SANDILE": [551, "ground", "dark", 0.7, 15.2, 5, 292],
  "KROKOROK": [552, "ground", "dark", 1.0, 33.4, 5, 351],
  "KROOKODILE": [553, "ground", "dark", 1.5, 96.3, 5, 519],
  "DARUMAKA": [554, "fire", "None", 0.6, 37.5, 5, 315],
  "DARMANITAN": [555, "fire", "fire", 1.3, 92.9, 5, 540],
  "MARACTUS": [556, "grass", "None", 1.0, 28.0, 5, 461],
  "DWEBBLE": [557, "bug", "rock", 0.3, 14.5, 5, 325],
  "CRUSTLE": [558, "bug", "rock", 1.4, 200.0, 5, 485],
  "SCRAGGY": [559, "dark", "fighting", 0.6, 11.8, 5, 348],
  "SCRAFTY": [560, "dark", "fighting", 1.1, 30.0, 5, 488],
  "SIGILYPH": [561, "psychic", "flying", 1.4, 14.0, 5, 490],
  "YAMASK": [562, "ghost", "None", 0.5, 1.5, 5, 303],
  "COFAGRIGUS": [563, "ghost", "None", 1.7, 76.5, 5, 483],
  "TIRTOUGA": [564, "water", "rock", 0.7, 16.5, 5, 355],
  "CARRACOSTA": [565, "water", "rock", 1.2, 81.0, 5, 495],
  "ARCHEN": [566, "rock", "flying", 0.5, 9.5, 5, 401],
  "ARCHEOPS": [567, "rock", "flying", 1.4, 32.0, 5, 567],
  "TRUBBISH": [568, "poison", "None", 0.6, 31.0, 5, 329],
  "GARBODOR": [569, "poison", "None", 1.9, 107.3, 5, 474],
  "ZORUA": [570, "dark", "None", 0.7, 12.5, 5, 330],
  "ZOROARK": [571, "dark", "None", 1.6, 81.1, 5, 510],
  "MINCCINO": [572, "normal", "None", 0.4, 5.8, 5, 300],
  "CINCCINO": [573, "normal", "None", 0.5, 7.5, 5, 470],
  "GOTHITA": [574, "psychic", "None", 0.4, 5.8, 5, 290],
  "GOTHORITA": [575, "psychic", "None", 0.7, 18.0, 5, 390],
  "GOTHITELLE": [576, "psychic", "None", 1.5, 44.0, 5, 490],
  "SOLOSIS": [577, "psychic", "None", 0.3, 1.0, 5, 290],
  "DUOSION": [578, "psychic", "None", 0.6, 8.0, 5, 370],
  "REUNICLUS": [579, "psychic", "None", 1.0, 20.1, 5, 490],
  "DUCKLETT": [580, "water", "flying", 0.5, 5.5, 5, 305],
  "SWANNA": [581, "water", "flying", 1.3, 24.2, 5, 473],
  "VANILLITE": [582, "ice", "None", 0.4, 5.7, 5, 305],
  "VANILLISH": [583, "ice", "None", 1.1, 41.0, 5, 395],
  "VANILLUXE": [584, "ice", "None", 1.3, 57.5, 5, 535],
  "DEERLING": [585, "normal", "grass", 0.6, 19.5, 5, 335],
  "SAWSBUCK": [586, "normal", "grass", 1.9, 92.5, 5, 475],
  "EMOLGA": [587, "electric", "flying", 0.4, 5.0, 5, 428],
  "KARRABLAST": [588, "bug", "None", 0.5, 5.9, 5, 315],
  "ESCAVALIER": [589, "bug", "steel", 1.0, 33.0, 5, 495],
  "FOONGUS": [590, "grass", "poison", 0.2, 1.0, 5, 294],
  "AMOONGUSS": [591, "grass", "poison", 0.6, 10.5, 5, 464],
  "FRILLISH": [592, "water", "ghost", 1.2, 33.0, 5, 335],
  "JELLICENT": [593, "water", "ghost", 2.2, 135.0, 5, 480],
  "ALOMOMOLA": [594, "water", "None", 1.2, 31.6, 5, 470],
  "JOLTIK": [595, "bug", "electric", 0.1, 0.6, 5, 319],
  "GALVANTULA": [596, "bug", "electric", 0.8, 14.3, 5, 472],
  "FERROSEED": [597, "grass", "steel", 0.6, 18.8, 5, 305],
  "FERROTHORN": [598, "grass", "steel", 1.0, 110.0, 5, 489],
  "KLINK": [599, "steel", "None", 0.3, 21.0, 5, 300],
  "KLANG": [600, "steel", "None", 0.6, 51.0, 5, 440],
  "KLINKLANG": [601, "steel", "None", 0.6, 81.0, 5, 520],
  "TYNAMO": [602, "electric", "None", 0.2, 0.3, 5, 275],
  "EELEKTRIK": [603, "electric", "None", 1.2, 22.0, 5, 405],
  "EELEKTROSS": [604, "electric", "None", 2.1, 80.5, 5, 515],
  "ELGYEM": [605, "psychic", "None", 0.5, 9.0, 5, 335],
  "BEHEEYEM": [606, "psychic", "None", 1.0, 34.5, 5, 485],
  "LITWICK": [607, "ghost", "fire", 0.3, 3.1, 5, 275],
  "LAMPENT": [608, "ghost", "fire", 0.6, 13.0, 5, 370],
  "CHANDELURE": [609, "ghost", "fire", 1.0, 34.3, 5, 520],
  "AXEW": [610, "dragon", "None", 0.6, 18.0, 5, 320],
  "FRAXURE": [611, "dragon", "None", 1.0, 36.0, 5, 410],
  "HAXORUS": [612, "dragon", "None", 1.8, 105.5, 5, 540],
  "CUBCHOO": [613, "ice", "None", 0.5, 8.5, 5, 305],
  "BEARTIC": [614, "ice", "None", 2.6, 260.0, 5, 505],
  "CRYOGONAL": [615, "ice", "None", 1.1, 148.0, 5, 515],
  "SHELMET": [616, "bug", "None", 0.4, 7.7, 5, 305],
  "ACCELGOR": [617, "bug", "None", 0.8, 25.3, 5, 495],
  "STUNFISK": [618, "ground", "electric", 0.7, 11.0, 5, 471],
  "MIENFOO": [619, "fighting", "None", 0.9, 20.0, 5, 350],
  "MIENSHAO": [620, "fighting", "None", 1.4, 35.5, 5, 510],
  "DRUDDIGON": [621, "dragon", "None", 1.6, 139.0, 5, 485],
  "GOLETT": [622, "ground", "ghost", 1.0, 92.0, 5, 303],
  "GOLURK": [623, "ground", "ghost", 2.8, 330.0, 5, 483],
  "PAWNIARD": [624, "dark", "steel", 0.5, 10.2, 5, 340],
  "BISHARP": [625, "dark", "steel", 1.6, 70.0, 5, 490],
  "BOUFFALANT": [626, "normal", "None", 1.6, 94.6, 5, 490],
  "RUFFLET": [627, "normal", "flying", 0.5, 10.5, 5, 350],
  "BRAVIARY": [628, "normal", "flying", 1.5, 41.0, 5, 510],
  "VULLABY": [629, "dark", "flying", 0.5, 9.0, 5, 370],
  "MANDIBUZZ": [630, "dark", "flying", 1.2, 39.5, 5, 510],
  "HEATMOR": [631, "fire", "None", 1.4, 58.0, 5, 484],
  "DURANT": [632, "bug", "steel", 0.3, 33.0, 5, 484],
  "DEINO": [633, "dark", "dragon", 0.8, 17.3, 5, 300],
  "ZWEILOUS": [634, "dark", "dragon", 1.4, 50.0, 5, 420],
  "HYDREIGON": [635, "dark", "dragon", 1.8, 160.0, 5, 600],
  "LARVESTA": [636, "bug", "fire", 1.1, 28.8, 5, 360],
  "VOLCARONA": [637, "bug", "fire", 1.6, 46.0, 5, 550],
  "COBALION": [638, "steel", "fighting", 2.1, 250.0, 5, 580],
  "TERRAKION": [639, "rock", "fighting", 1.9, 260.0, 5, 580],
  "VIRIZION": [640, "grass", "fighting", 2.0, 200.0, 5, 580],
  "TORNADUS": [641, "flying", "None", 1.5, 63.0, 5, 580],
  "THUNDURUS": [642, "electric", "flying", 1.5, 61.0, 5, 580],
  "RESHIRAM": [643, "dragon", "fire", 3.2, 330.0, 5, 680],
  "ZEKROM": [644, "dragon", "electric", 2.9, 345.0, 5, 680],
  "LANDORUS": [645, "ground", "flying", 1.5, 68.0, 5, 600],
  "KYUREM": [646, "dragon", "ice", 3.0, 325.0, 5, 700],
  "KELDEO": [647, "water", "fighting", 1.4, 48.5, 5, 580],
  "MELOETTA": [648, "normal", "psychic", 0.6, 6.5, 5, 600],
  "GENESECT": [649, "bug", "steel", 1.5, 82.5, 5, 600],
  "CHESPIN": [650, "grass", "None", 0.4, 9.0, 6, 313],
  "QUILLADIN": [651, "grass", "None", 0.7, 29.0, 6, 405],
  "CHESNAUGHT": [652, "grass", "fighting", 1.6, 90.0, 6, 530],
  "FENNEKIN": [653, "fire", "None", 0.4, 9.4, 6, 307],
  "BRAIXEN": [654, "fire", "None", 1.0, 14.5, 6, 409],
  "DELPHOX": [655, "fire", "psychic", 1.5, 39.0, 6, 534],
  "FROAKIE": [656, "water", "None", 0.3, 7.0, 6, 314],
  "FROGADIER": [657, "water", "None", 0.6, 10.9, 6, 405],
  "GRENINJA": [658, "water", "dark", 1.5, 40.0, 6, 640],
  "BUNNELBY": [659, "normal", "None", 0.4, 5.0, 6, 237],
  "DIGGERSBY": [660, "normal", "ground", 1.0, 42.4, 6, 423],
  "FLETCHLING": [661, "normal", "flying", 0.3, 1.7, 6, 278],
  "FLETCHINDER": [662, "fire", "flying", 0.7, 16.0, 6, 382],
  "TALONFLAME": [663, "fire", "flying", 1.2, 24.5, 6, 499],
  "SCATTERBUG": [664, "bug", "None", 0.3, 2.5, 6, 200],
  "SPEWPA": [665, "bug", "None", 0.3, 8.4, 6, 213],
  "VIVILLON": [666, "bug", "flying", 1.2, 17.0, 6, 411],
  "LITLEO": [667, "fire", "normal", 0.6, 13.5, 6, 369],
  "PYROAR": [668, "fire", "normal", 1.5, 81.5, 6, 507],
  "FLAB\u00c9B\u00c9": [669, "fairy", "None", 0.1, 0.1, 6, 303],
  "FLOETTE": [670, "fairy", "None", 0.2, 0.9, 6, 551],
  "FLORGES": [671, "fairy", "None", 1.1, 10.0, 6, 552],
  "SKIDDO": [672, "grass", "None", 0.9, 31.0, 6, 350],
  "GOGOAT": [673, "grass", "None", 1.7, 91.0, 6, 531],
  "PANCHAM": [674, "fighting", "None", 0.6, 8.0, 6, 348],
  "PANGORO": [675, "fighting", "dark", 2.1, 136.0, 6, 495],
  "FURFROU": [676, "normal", "None", 1.2, 28.0, 6, 472],
  "ESPURR": [677, "psychic", "None", 0.3, 3.5, 6, 355],
  "MEOWSTIC": [678, "psychic", "None", 0.6, 8.5, 6, 466],
  "HONEDGE": [679, "steel", "ghost", 0.8, 2.0, 6, 325],
  "DOUBLADE": [680, "steel", "ghost", 0.8, 4.5, 6, 448],
  "AEGISLASH": [681, "steel", "ghost", 1.7, 53.0, 6, 520],
  "SPRITZEE": [682, "fairy", "None", 0.2, 0.5, 6, 341],
  "AROMATISSE": [683, "fairy", "None", 0.8, 15.5, 6, 462],
  "SWIRLIX": [684, "fairy", "None", 0.4, 3.5, 6, 341],
  "SLURPUFF": [685, "fairy", "None", 0.8, 5.0, 6, 480],
  "INKAY": [686, "dark", "psychic", 0.4, 3.5, 6, 288],
  "MALAMAR": [687, "dark", "psychic", 1.5, 47.0, 6, 482],
  "BINACLE": [688, "rock", "water", 0.5, 31.0, 6, 306],
  "BARBARACLE": [689, "rock", "water", 1.3, 96.0, 6, 500],
  "SKRELP": [690, "poison", "water", 0.5, 7.3, 6, 320],
  "DRAGALGE": [691, "poison", "dragon", 1.8, 81.5, 6, 494],
  "CLAUNCHER": [692, "water", "None", 0.5, 8.3, 6, 330],
  "CLAWITZER": [693, "water", "None", 1.3, 35.3, 6, 500],
  "HELIOPTILE": [694, "electric", "normal", 0.5, 6.0, 6, 289],
  "HELIOLISK": [695, "electric", "normal", 1.0, 21.0, 6, 481],
  "TYRUNT": [696, "rock", "dragon", 0.8, 26.0, 6, 362],
  "TYRANTRUM": [697, "rock", "dragon", 2.5, 270.0, 6, 521],
  "AMAURA": [698, "rock", "ice", 1.3, 25.2, 6, 362],
  "AURORUS": [699, "rock", "ice", 2.7, 225.0, 6, 521],
  "SYLVEON": [700, "fairy", "None", 1.0, 23.5, 6, 525],
  "HAWLUCHA": [701, "fighting", "flying", 0.8, 21.5, 6, 500],
  "DEDENNE": [702, "electric", "fairy", 0.2, 2.2, 6, 431],
  "CARBINK": [703, "rock", "fairy", 0.3, 5.7, 6, 500],
  "GOOMY": [704, "dragon", "None", 0.3, 2.8, 6, 300],
  "SLIGGOO": [705, "dragon", "None", 0.8, 17.5, 6, 452],
  "GOODRA": [706, "dragon", "None", 2.0, 150.5, 6, 600],
  "KLEFKI": [707, "steel", "fairy", 0.2, 3.0, 6, 470],
  "PHANTUMP": [708, "ghost", "grass", 0.4, 7.0, 6, 309],
  "TREVENANT": [709, "ghost", "grass", 1.5, 71.0, 6, 474],
  "PUMPKABOO": [710, "ghost", "grass", 0.8, 15.0, 6, 335],
  "GOURGEIST": [711, "ghost", "grass", 1.7, 39.0, 6, 494],
  "BERGMITE": [712, "ice", "None", 1.0, 99.5, 6, 304],
  "AVALUGG": [713, "ice", "None", 2.0, 505.0, 6, 514],
  "NOIBAT": [714, "flying", "dragon", 0.5, 8.0, 6, 245],
  "NOIVERN": [715, "flying", "dragon", 1.5, 85.0, 6, 535],
  "XERNEAS": [716, "fairy", "None", 3.0, 215.0, 6, 680],
  "YVELTAL": [717, "dark", "flying", 5.8, 203.0, 6, 680],
  "ZYGARDE": [718, "dragon", "ground", 5.0, 284.6, 6, 708],
  "DIANCIE": [719, "rock", "fairy", 0.7, 8.8, 6, 700],
  "HOOPA": [720, "psychic", "ghost", NaN, NaN, 6, 680],
  "VOLCANION": [721, "fire", "water", 1.7, 195.0, 6, 600],
  "ROWLET": [722, "grass", "flying", 0.3, 1.5, 7, 320],
  "DARTRIX": [723, "grass", "flying", 0.7, 16.0, 7, 420],
  "DECIDUEYE": [724, "grass", "ghost", 1.6, 36.6, 7, 530],
  "LITTEN": [725, "fire", "None", 0.4, 4.3, 7, 320],
  "TORRACAT": [726, "fire", "None", 0.7, 25.0, 7, 420],
  "INCINEROAR": [727, "fire", "dark", 1.8, 83.0, 7, 530],
  "POPPLIO": [728, "water", "None", 0.4, 7.5, 7, 320],
  "BRIONNE": [729, "water", "None", 0.6, 17.5, 7, 420],
  "PRIMARINA": [730, "water", "fairy", 1.8, 44.0, 7, 530],
  "PIKIPEK": [731, "normal", "flying", 0.3, 1.2, 7, 265],
  "TRUMBEAK": [732, "normal", "flying", 0.6, 14.8, 7, 355],
  "TOUCANNON": [733, "normal", "flying", 1.1, 26.0, 7, 485],
  "YUNGOOS": [734, "normal", "None", 0.4, 6.0, 7, 253],
  "GUMSHOOS": [735, "normal", "None", 0.7, 14.2, 7, 418],
  "GRUBBIN": [736, "bug", "None", 0.4, 4.4, 7, 300],
  "CHARJABUG": [737, "bug", "electric", 0.5, 10.5, 7, 400],
  "VIKAVOLT": [738, "bug", "electric", 1.5, 45.0, 7, 500],
  "CRABRAWLER": [739, "fighting", "None", 0.6, 7.0, 7, 338],
  "CRABOMINABLE": [740, "fighting", "ice", 1.7, 180.0, 7, 478],
  "ORICORIO": [741, "fire", "flying", 0.6, 3.4, 7, 476],
  "CUTIEFLY": [742, "bug", "fairy", 0.1, 0.2, 7, 304],
  "RIBOMBEE": [743, "bug", "fairy", 0.2, 0.5, 7, 464],
  "ROCKRUFF": [744, "rock", "None", 0.5, 9.2, 7, 280],
  "LYCANROC": [745, "rock", "None", NaN, NaN, 7, 487],
  "WISHIWASHI": [746, "water", "None", 0.2, 0.3, 7, 620],
  "MAREANIE": [747, "poison", "water", 0.4, 8.0, 7, 305],
  "TOXAPEX": [748, "poison", "water", 0.7, 14.5, 7, 495],
  "MUDBRAY": [749, "ground", "None", 1.0, 110.0, 7, 385],
  "MUDSDALE": [750, "ground", "None", 2.5, 920.0, 7, 500],
  "DEWPIDER": [751, "water", "bug", 0.3, 4.0, 7, 269],
  "ARAQUANID": [752, "water", "bug", 1.8, 82.0, 7, 454],
  "FOMANTIS": [753, "grass", "None", 0.3, 1.5, 7, 250],
  "LURANTIS": [754, "grass", "None", 0.9, 18.5, 7, 480],
  "MORELULL": [755, "grass", "fairy", 0.2, 1.5, 7, 285],
  "SHIINOTIC": [756, "grass", "fairy", 1.0, 11.5, 7, 405],
  "SALANDIT": [757, "poison", "fire", 0.6, 4.8, 7, 320],
  "SALAZZLE": [758, "poison", "fire", 1.2, 22.2, 7, 480],
  "STUFFUL": [759, "normal", "fighting", 0.5, 6.8, 7, 340],
  "BEWEAR": [760, "normal", "fighting", 2.1, 135.0, 7, 500],
  "BOUNSWEET": [761, "grass", "None", 0.3, 3.2, 7, 210],
  "STEENEE": [762, "grass", "None", 0.7, 8.2, 7, 290],
  "TSAREENA": [763, "grass", "None", 1.2, 21.4, 7, 510],
  "COMFEY": [764, "fairy", "None", 0.1, 0.3, 7, 485],
  "ORANGURU": [765, "normal", "psychic", 1.5, 76.0, 7, 490],
  "PASSIMIAN": [766, "fighting", "None", 2.0, 82.8, 7, 490],
  "WIMPOD": [767, "bug", "water", 0.5, 12.0, 7, 230],
  "GOLISOPOD": [768, "bug", "water", 2.0, 108.0, 7, 530],
  "SANDYGAST": [769, "ghost", "ground", 0.5, 70.0, 7, 320],
  "PALOSSAND": [770, "ghost", "ground", 1.3, 250.0, 7, 480],
  "PYUKUMUKU": [771, "water", "None", 0.3, 1.2, 7, 410],
  "TYPE: NULL": [772, "normal", "None", 1.9, 120.5, 7, 534],
  "SILVALLY": [773, "normal", "None", 2.3, 100.5, 7, 570],
  "MINIOR": [774, "rock", "flying", 0.3, 40.0, 7, 500],
  "KOMALA": [775, "normal", "None", 0.4, 19.9, 7, 480],
  "TURTONATOR": [776, "fire", "dragon", 2.0, 212.0, 7, 485],
  "TOGEDEMARU": [777, "electric", "steel", 0.3, 3.3, 7, 435],
  "MIMIKYU": [778, "ghost", "fairy", 0.2, 0.7, 7, 476],
  "BRUXISH": [779, "water", "psychic", 0.9, 19.0, 7, 475],
  "DRAMPA": [780, "normal", "dragon", 3.0, 185.0, 7, 485],
  "DHELMISE": [781, "ghost", "grass", 3.9, 210.0, 7, 517],
  "JANGMO-O": [782, "dragon", "None", 0.6, 29.7, 7, 300],
  "HAKAMO-O": [783, "dragon", "fighting", 1.2, 47.0, 7, 420],
  "KOMMO-O": [784, "dragon", "fighting", 1.6, 78.2, 7, 600],
  "TAPU KOKO": [785, "electric", "fairy", 1.8, 20.5, 7, 570],
  "TAPU LELE": [786, "psychic", "fairy", 1.2, 18.6, 7, 570],
  "TAPU BULU": [787, "grass", "fairy", 1.9, 45.5, 7, 570],
  "TAPU FINI": [788, "water", "fairy", 1.3, 21.2, 7, 570],
  "COSMOG": [789, "psychic", "None", 0.2, 0.1, 7, 200],
  "COSMOEM": [790, "psychic", "None", 0.1, 999.9, 7, 400],
  "SOLGALEO": [791, "psychic", "steel", 3.4, 230.0, 7, 680],
  "LUNALA": [792, "psychic", "ghost", 4.0, 120.0, 7, 680],
  "NIHILEGO": [793, "rock", "poison", 1.2, 55.5, 7, 570],
  "BUZZWOLE": [794, "bug", "fighting", 2.4, 333.6, 7, 570],
  "PHEROMOSA": [795, "bug", "fighting", 1.8, 25.0, 7, 570],
  "XURKITREE": [796, "electric", "None", 3.8, 100.0, 7, 570],
  "CELESTEELA": [797, "steel", "flying", 9.2, 999.9, 7, 570],
  "KARTANA": [798, "grass", "steel", 0.3, 0.1, 7, 570],
  "GUZZLORD": [799, "dark", "dragon", 5.5, 888.0, 7, 570],
  "NECROZMA": [800, "psychic", "None", 2.4, 230.0, 7, 600],
  "MAGEARNA": [801, "steel", "fairy", 1.0, 80.5, 7, 600]
}
